controller/__init__.py
controller/core/__init__.py
controller/core/db.py
controller/core/fields.py
controller/core/functions.py
controller/core/models.py
controller/django/__init__.py
controller/django/db.py
controller/django/fields.py
controller/django/middleware.py
controller/django/models.py
functionstoredcontroller-0.0.12.dist-info/LICENSE
functionstoredcontroller-0.0.12.dist-info/WHEEL
functionstoredcontroller-0.0.12.dist-info/METADATA
functionstoredcontroller-0.0.12.dist-info/RECORD
