Metadata-Version: 2.1
Name: FunctionStoredController
Version: 0.0.12
Summary: Контроллер для работы с хранимыми процедурами
Author-email: DigoErisdar <danil.galkin2017@mail.ru>
Classifier: License :: OSI Approved :: MIT License
Project-URL: Home, https://github.com/DigoErisdar/Controller
